<?xml version="1.0" encoding="UTF-8"?><record_update table="wf_workflow_version">
    <wf_workflow_version action="INSERT_OR_UPDATE">
        <active>true</active>
        <activity_stages>{"ends":["cf1a96b0db67b700b26388805b961996"],"activities":{},"stages":{},"subflows":[]}</activity_stages>
        <after_business_rules>false</after_business_rules>
        <checked_out/>
        <checked_out_by/>
        <column_renderer display_value="Legacy">007c2f021b020100adca1e094f0713b4</column_renderer>
        <condition table="x_ipegh_copyright_qc">u_error_found_atISNOTEMPTY^u_corrected=false^active=true^EQ<item endquery="false" field="u_error_found_at" goto="false" newquery="false" operator="ISNOTEMPTY" or="false" value=""/>
            <item endquery="false" field="u_corrected" goto="false" newquery="false" operator="=" or="false" value="false"/>
            <item endquery="false" field="active" goto="false" newquery="false" operator="=" or="false" value="true"/>
            <item endquery="true" field="" goto="false" newquery="false" operator="=" or="false" value=""/>
        </condition>
        <condition_type>run_match</condition_type>
        <description>Workflow to remind the User to amend the error</description>
        <expected_sequences>c71a12b0db67b700b26388805b9619a5,4b1a12b0db67b700b26388805b96199e,c71a12b0db67b700b26388805b9619a2,0f1a12b0db67b700b26388805b9619a4,431a12b0db67b700b26388805b9619a6,cf1a96b0db67b700b26388805b961996,8b1a12b0db67b700b26388805b9619a3</expected_sequences>
        <expected_time>1970-01-06 00:00:00</expected_time>
        <expected_time_type/>
        <full_sequences>c71a12b0db67b700b26388805b9619a5,4b1a12b0db67b700b26388805b96199e,c71a12b0db67b700b26388805b9619a2,0f1a12b0db67b700b26388805b9619a4,431a12b0db67b700b26388805b9619a6,cf1a96b0db67b700b26388805b961996,8b1a12b0db67b700b26388805b9619a3</full_sequences>
        <journal/>
        <max_activity_count>100</max_activity_count>
        <name>QC app reminder wf</name>
        <not_cacheable>false</not_cacheable>
        <on_cancel><![CDATA[// This script executes if the workflow is cancelled.// The global variable context_sys_id contains the sys_id of the cancelled workflow context.]]></on_cancel>
        <order>100</order>
        <pin_type>set_by_activity</pin_type>
        <published>true</published>
        <relative_duration display_value="2 business days by 4pm">3bf802c20a0a0b52008e2859cd8abcf2</relative_duration>
        <requires_ert>true</requires_ert>
        <run_multiple>false</run_multiple>
        <schedule display_value="ICE Working Hours - Germany">fef684a3dbdf1b00b26388805b9619ec</schedule>
        <stage_field/>
        <stage_order>computed</stage_order>
        <start display_value="Begin">c71a12b0db67b700b26388805b9619a5</start>
        <sys_created_by>LasBal</sys_created_by>
        <sys_created_on>2019-08-26 09:35:49</sys_created_on>
        <sys_id>c31a12b0db67b700b26388805b96199d</sys_id>
        <sys_mod_count>6</sys_mod_count>
        <sys_updated_by>LasBal</sys_updated_by>
        <sys_updated_on>2019-08-26 09:39:30</sys_updated_on>
        <table>x_ipegh_copyright_qc</table>
        <timezone/>
        <validated>true</validated>
        <workflow display_value="QC app reminder wf">a8daaf7adbd7f340b26388805b961974</workflow>
    </wf_workflow_version>
    <wf_workflow action="INSERT_OR_UPDATE">
        <access>public</access>
        <description>Workflow to remind the User to amend the error</description>
        <name>QC app reminder wf</name>
        <preview/>
        <sys_class_name>wf_workflow</sys_class_name>
        <sys_created_by>AnnAal</sys_created_by>
        <sys_created_on>2019-08-20 10:20:36</sys_created_on>
        <sys_domain>global</sys_domain>
        <sys_domain_path>/</sys_domain_path>
        <sys_id>a8daaf7adbd7f340b26388805b961974</sys_id>
        <sys_mod_count>3</sys_mod_count>
        <sys_name>QC app reminder wf</sys_name>
        <sys_overrides/>
        <sys_package display_value="Copyright QC" source="x_ipegh_copyright">5cb9a113db8e3b00b26388805b9619f0</sys_package>
        <sys_policy/>
        <sys_scope display_value="Copyright QC">5cb9a113db8e3b00b26388805b9619f0</sys_scope>
        <sys_update_name>wf_workflow_a8daaf7adbd7f340b26388805b961974</sys_update_name>
        <sys_updated_by>AnnAal</sys_updated_by>
        <sys_updated_on>2019-08-20 11:47:35</sys_updated_on>
        <table>x_ipegh_copyright_qc</table>
        <template>false</template>
        <vars/>
    </wf_workflow>
    <wf_activity action="INSERT_OR_UPDATE">
        <activity_definition display_value="Begin">c7a5e32c0a0a0b3a002377c24ed8ea76</activity_definition>
        <activity_definition_updated>false</activity_definition_updated>
        <databus_lookup_id/>
        <height/>
        <input/>
        <is_parent>false</is_parent>
        <name>Begin</name>
        <new_activity_definition/>
        <notes/>
        <out_of_date>false</out_of_date>
        <parent/>
        <pinned>false</pinned>
        <pinned_version/>
        <stage/>
        <sys_created_by>LasBal</sys_created_by>
        <sys_created_on>2019-08-26 09:35:50</sys_created_on>
        <sys_id>c71a12b0db67b700b26388805b9619a5</sys_id>
        <sys_mod_count>0</sys_mod_count>
        <sys_updated_by>LasBal</sys_updated_by>
        <sys_updated_on>2019-08-26 09:35:50</sys_updated_on>
        <timeout>1970-01-01 00:00:00</timeout>
        <vars/>
        <width>80</width>
        <workflow_version display_value="QC app reminder wf">c31a12b0db67b700b26388805b96199d</workflow_version>
        <x>6</x>
        <y>20</y>
    </wf_activity>
    <sys_variable_value action="delete_multiple" query="document_key=c71a12b0db67b700b26388805b9619a5"/>
    <wf_condition action="INSERT_OR_UPDATE">
        <activity display_value="Begin">c71a12b0db67b700b26388805b9619a5</activity>
        <condition>true</condition>
        <condition_default/>
        <condition_type>standard</condition_type>
        <else_flag>false</else_flag>
        <error>false</error>
        <event>false</event>
        <event_name/>
        <is_positive>false</is_positive>
        <name>Always</name>
        <order>0</order>
        <short_description/>
        <skip_during_generate>false</skip_during_generate>
        <sys_created_by>LasBal</sys_created_by>
        <sys_created_on>2019-08-26 09:35:50</sys_created_on>
        <sys_id>8b1a12b0db67b700b26388805b9619a5</sys_id>
        <sys_mod_count>0</sys_mod_count>
        <sys_updated_by>LasBal</sys_updated_by>
        <sys_updated_on>2019-08-26 09:35:50</sys_updated_on>
    </wf_condition>
    <wf_activity action="INSERT_OR_UPDATE">
        <activity_definition display_value="End">c7a66f7d0a0a0b3a004544a6d2f14076</activity_definition>
        <activity_definition_updated>false</activity_definition_updated>
        <databus_lookup_id/>
        <height/>
        <input/>
        <is_parent>false</is_parent>
        <name>End</name>
        <new_activity_definition/>
        <notes/>
        <out_of_date>false</out_of_date>
        <parent/>
        <pinned>false</pinned>
        <pinned_version/>
        <stage/>
        <sys_created_by>LasBal</sys_created_by>
        <sys_created_on>2019-08-26 09:35:50</sys_created_on>
        <sys_id>cf1a96b0db67b700b26388805b961996</sys_id>
        <sys_mod_count>0</sys_mod_count>
        <sys_updated_by>LasBal</sys_updated_by>
        <sys_updated_on>2019-08-26 09:35:50</sys_updated_on>
        <timeout>1970-01-01 00:00:00</timeout>
        <vars/>
        <width>80</width>
        <workflow_version display_value="QC app reminder wf">c31a12b0db67b700b26388805b96199d</workflow_version>
        <x>1454</x>
        <y>601</y>
    </wf_activity>
    <sys_variable_value action="delete_multiple" query="document_key=cf1a96b0db67b700b26388805b961996"/>
    <wf_activity action="INSERT_OR_UPDATE">
        <activity_definition display_value="Create Event">9f680b92c0a801640026553f665b429f</activity_definition>
        <activity_definition_updated>false</activity_definition_updated>
        <databus_lookup_id>12</databus_lookup_id>
        <height/>
        <input>{}</input>
        <is_parent>false</is_parent>
        <name>Notify User</name>
        <new_activity_definition/>
        <notes/>
        <out_of_date>false</out_of_date>
        <parent/>
        <pinned>false</pinned>
        <pinned_version/>
        <stage/>
        <sys_created_by>LasBal</sys_created_by>
        <sys_created_on>2019-08-26 09:35:50</sys_created_on>
        <sys_id>c71a12b0db67b700b26388805b9619a2</sys_id>
        <sys_mod_count>0</sys_mod_count>
        <sys_updated_by>LasBal</sys_updated_by>
        <sys_updated_on>2019-08-26 09:35:50</sys_updated_on>
        <timeout>1970-01-01 00:00:00</timeout>
        <vars/>
        <width/>
        <workflow_version display_value="QC app reminder wf">c31a12b0db67b700b26388805b96199d</workflow_version>
        <x>673</x>
        <y>246</y>
    </wf_activity>
    <sys_variable_value action="delete_multiple" query="document_key=c71a12b0db67b700b26388805b9619a2"/>
    <sys_variable_value action="INSERT_OR_UPDATE">
        <document>wf_activity</document>
        <document_key>c71a12b0db67b700b26388805b9619a2</document_key>
        <order>200</order>
        <sys_class_name>sys_variable_value</sys_class_name>
        <sys_created_by>LasBal</sys_created_by>
        <sys_created_on>2019-08-26 09:35:50</sys_created_on>
        <sys_id>0f1a12b0db67b700b26388805b9619a2</sys_id>
        <sys_mod_count>0</sys_mod_count>
        <sys_updated_by>LasBal</sys_updated_by>
        <sys_updated_on>2019-08-26 09:35:50</sys_updated_on>
        <value>current.user;&#13;
</value>
        <variable display_value="">c35dd0310a0a0ba96248a70936d276b3</variable>
    </sys_variable_value>
    <sys_variable_value action="INSERT_OR_UPDATE">
        <document>wf_activity</document>
        <document_key>c71a12b0db67b700b26388805b9619a2</document_key>
        <order>100</order>
        <sys_class_name>sys_variable_value</sys_class_name>
        <sys_created_by>LasBal</sys_created_by>
        <sys_created_on>2019-08-26 09:35:50</sys_created_on>
        <sys_id>4b1a12b0db67b700b26388805b9619a2</sys_id>
        <sys_mod_count>0</sys_mod_count>
        <sys_updated_by>LasBal</sys_updated_by>
        <sys_updated_on>2019-08-26 09:35:50</sys_updated_on>
        <value>3261fb32db1bf340b26388805b961975</value>
        <variable display_value="">c35dcc7a0a0a0ba96248a70926fa68b5</variable>
    </sys_variable_value>
    <sys_variable_value action="INSERT_OR_UPDATE">
        <document>wf_activity</document>
        <document_key>c71a12b0db67b700b26388805b9619a2</document_key>
        <order>300</order>
        <sys_class_name>sys_variable_value</sys_class_name>
        <sys_created_by>LasBal</sys_created_by>
        <sys_created_on>2019-08-26 09:35:50</sys_created_on>
        <sys_id>cf1a12b0db67b700b26388805b9619a2</sys_id>
        <sys_mod_count>0</sys_mod_count>
        <sys_updated_by>LasBal</sys_updated_by>
        <sys_updated_on>2019-08-26 09:35:50</sys_updated_on>
        <value>(function() {&#13;
	// return the value to use for Parameter 2&#13;
	return "";&#13;
}());</value>
        <variable display_value="">c35dd3ef0a0a0ba96248a70947e35325</variable>
    </sys_variable_value>
    <sys_variable_value action="INSERT_OR_UPDATE">
        <document>wf_activity</document>
        <document_key>c71a12b0db67b700b26388805b9619a2</document_key>
        <order>100</order>
        <sys_class_name>sys_variable_value</sys_class_name>
        <sys_created_by>LasBal</sys_created_by>
        <sys_created_on>2019-08-26 09:35:50</sys_created_on>
        <sys_id>4b1a12b0db67b700b26388805b9619a2</sys_id>
        <sys_mod_count>0</sys_mod_count>
        <sys_updated_by>LasBal</sys_updated_by>
        <sys_updated_on>2019-08-26 09:35:50</sys_updated_on>
        <value>3261fb32db1bf340b26388805b961975</value>
        <variable display_value="">c35dcc7a0a0a0ba96248a70926fa68b5</variable>
    </sys_variable_value>
    <sys_variable_value action="INSERT_OR_UPDATE">
        <document>wf_activity</document>
        <document_key>c71a12b0db67b700b26388805b9619a2</document_key>
        <order>200</order>
        <sys_class_name>sys_variable_value</sys_class_name>
        <sys_created_by>LasBal</sys_created_by>
        <sys_created_on>2019-08-26 09:35:50</sys_created_on>
        <sys_id>0f1a12b0db67b700b26388805b9619a2</sys_id>
        <sys_mod_count>0</sys_mod_count>
        <sys_updated_by>LasBal</sys_updated_by>
        <sys_updated_on>2019-08-26 09:35:50</sys_updated_on>
        <value>current.user;&#13;
</value>
        <variable display_value="">c35dd0310a0a0ba96248a70936d276b3</variable>
    </sys_variable_value>
    <sys_variable_value action="INSERT_OR_UPDATE">
        <document>wf_activity</document>
        <document_key>c71a12b0db67b700b26388805b9619a2</document_key>
        <order>300</order>
        <sys_class_name>sys_variable_value</sys_class_name>
        <sys_created_by>LasBal</sys_created_by>
        <sys_created_on>2019-08-26 09:35:50</sys_created_on>
        <sys_id>cf1a12b0db67b700b26388805b9619a2</sys_id>
        <sys_mod_count>0</sys_mod_count>
        <sys_updated_by>LasBal</sys_updated_by>
        <sys_updated_on>2019-08-26 09:35:50</sys_updated_on>
        <value>(function() {&#13;
	// return the value to use for Parameter 2&#13;
	return "";&#13;
}());</value>
        <variable display_value="">c35dd3ef0a0a0ba96248a70947e35325</variable>
    </sys_variable_value>
    <wf_condition action="INSERT_OR_UPDATE">
        <activity display_value="Notify User">c71a12b0db67b700b26388805b9619a2</activity>
        <condition>true</condition>
        <condition_default/>
        <condition_type>standard</condition_type>
        <else_flag>false</else_flag>
        <error>false</error>
        <event>false</event>
        <event_name/>
        <is_positive>true</is_positive>
        <name>Always</name>
        <order>0</order>
        <short_description/>
        <skip_during_generate>false</skip_during_generate>
        <sys_created_by>LasBal</sys_created_by>
        <sys_created_on>2019-08-26 09:35:50</sys_created_on>
        <sys_id>c31a12b0db67b700b26388805b9619a3</sys_id>
        <sys_mod_count>0</sys_mod_count>
        <sys_updated_by>LasBal</sys_updated_by>
        <sys_updated_on>2019-08-26 09:35:50</sys_updated_on>
    </wf_condition>
    <wf_activity action="INSERT_OR_UPDATE">
        <activity_definition display_value="Create Event">9f680b92c0a801640026553f665b429f</activity_definition>
        <activity_definition_updated>false</activity_definition_updated>
        <databus_lookup_id>9</databus_lookup_id>
        <height/>
        <input>{}</input>
        <is_parent>false</is_parent>
        <name>Notify User, Assignee and User.Manager</name>
        <new_activity_definition/>
        <notes/>
        <out_of_date>false</out_of_date>
        <parent/>
        <pinned>false</pinned>
        <pinned_version/>
        <stage/>
        <sys_created_by>LasBal</sys_created_by>
        <sys_created_on>2019-08-26 09:35:50</sys_created_on>
        <sys_id>8b1a12b0db67b700b26388805b9619a3</sys_id>
        <sys_mod_count>1</sys_mod_count>
        <sys_updated_by>LasBal</sys_updated_by>
        <sys_updated_on>2019-08-26 09:38:40</sys_updated_on>
        <timeout>1970-01-01 00:00:00</timeout>
        <vars/>
        <width/>
        <workflow_version display_value="QC app reminder wf">c31a12b0db67b700b26388805b96199d</workflow_version>
        <x>1135</x>
        <y>227</y>
    </wf_activity>
    <sys_variable_value action="delete_multiple" query="document_key=8b1a12b0db67b700b26388805b9619a3"/>
    <sys_variable_value action="INSERT_OR_UPDATE">
        <document>wf_activity</document>
        <document_key>8b1a12b0db67b700b26388805b9619a3</document_key>
        <order>100</order>
        <sys_class_name>sys_variable_value</sys_class_name>
        <sys_created_by>LasBal</sys_created_by>
        <sys_created_on>2019-08-26 09:35:50</sys_created_on>
        <sys_id>0f1a12b0db67b700b26388805b9619a3</sys_id>
        <sys_mod_count>0</sys_mod_count>
        <sys_updated_by>LasBal</sys_updated_by>
        <sys_updated_on>2019-08-26 09:35:50</sys_updated_on>
        <value>3261fb32db1bf340b26388805b961975</value>
        <variable display_value="">c35dcc7a0a0a0ba96248a70926fa68b5</variable>
    </sys_variable_value>
    <sys_variable_value action="INSERT_OR_UPDATE">
        <document>wf_activity</document>
        <document_key>8b1a12b0db67b700b26388805b9619a3</document_key>
        <order>300</order>
        <sys_class_name>sys_variable_value</sys_class_name>
        <sys_created_by>LasBal</sys_created_by>
        <sys_created_on>2019-08-26 09:35:50</sys_created_on>
        <sys_id>831a12b0db67b700b26388805b9619a4</sys_id>
        <sys_mod_count>0</sys_mod_count>
        <sys_updated_by>LasBal</sys_updated_by>
        <sys_updated_on>2019-08-26 09:35:50</sys_updated_on>
        <value>(function() {&#13;
	// return the value to use for Parameter 2&#13;
	return "";&#13;
}());</value>
        <variable display_value="">c35dd3ef0a0a0ba96248a70947e35325</variable>
    </sys_variable_value>
    <sys_variable_value action="INSERT_OR_UPDATE">
        <document>wf_activity</document>
        <document_key>8b1a12b0db67b700b26388805b9619a3</document_key>
        <order>200</order>
        <sys_class_name>sys_variable_value</sys_class_name>
        <sys_created_by>LasBal</sys_created_by>
        <sys_created_on>2019-08-26 09:35:50</sys_created_on>
        <sys_id>cf1a12b0db67b700b26388805b9619a3</sys_id>
        <sys_mod_count>1</sys_mod_count>
        <sys_updated_by>LasBal</sys_updated_by>
        <sys_updated_on>2019-08-26 09:38:40</sys_updated_on>
        <value>(function() {&#13;
	var usr = current.user;&#13;
	var asgnd = current.assigned_to;&#13;
	var mgr = current.user.manager;&#13;
	var p1 = usr + ',' + asgnd + ',' + mgr;&#13;
	return "p1";&#13;
}());&#13;
</value>
        <variable display_value="">c35dd0310a0a0ba96248a70936d276b3</variable>
    </sys_variable_value>
    <sys_variable_value action="INSERT_OR_UPDATE">
        <document>wf_activity</document>
        <document_key>8b1a12b0db67b700b26388805b9619a3</document_key>
        <order>100</order>
        <sys_class_name>sys_variable_value</sys_class_name>
        <sys_created_by>LasBal</sys_created_by>
        <sys_created_on>2019-08-26 09:35:50</sys_created_on>
        <sys_id>0f1a12b0db67b700b26388805b9619a3</sys_id>
        <sys_mod_count>0</sys_mod_count>
        <sys_updated_by>LasBal</sys_updated_by>
        <sys_updated_on>2019-08-26 09:35:50</sys_updated_on>
        <value>3261fb32db1bf340b26388805b961975</value>
        <variable display_value="">c35dcc7a0a0a0ba96248a70926fa68b5</variable>
    </sys_variable_value>
    <sys_variable_value action="INSERT_OR_UPDATE">
        <document>wf_activity</document>
        <document_key>8b1a12b0db67b700b26388805b9619a3</document_key>
        <order>200</order>
        <sys_class_name>sys_variable_value</sys_class_name>
        <sys_created_by>LasBal</sys_created_by>
        <sys_created_on>2019-08-26 09:35:50</sys_created_on>
        <sys_id>cf1a12b0db67b700b26388805b9619a3</sys_id>
        <sys_mod_count>1</sys_mod_count>
        <sys_updated_by>LasBal</sys_updated_by>
        <sys_updated_on>2019-08-26 09:38:40</sys_updated_on>
        <value>(function() {&#13;
	var usr = current.user;&#13;
	var asgnd = current.assigned_to;&#13;
	var mgr = current.user.manager;&#13;
	var p1 = usr + ',' + asgnd + ',' + mgr;&#13;
	return "p1";&#13;
}());&#13;
</value>
        <variable display_value="">c35dd0310a0a0ba96248a70936d276b3</variable>
    </sys_variable_value>
    <sys_variable_value action="INSERT_OR_UPDATE">
        <document>wf_activity</document>
        <document_key>8b1a12b0db67b700b26388805b9619a3</document_key>
        <order>300</order>
        <sys_class_name>sys_variable_value</sys_class_name>
        <sys_created_by>LasBal</sys_created_by>
        <sys_created_on>2019-08-26 09:35:50</sys_created_on>
        <sys_id>831a12b0db67b700b26388805b9619a4</sys_id>
        <sys_mod_count>0</sys_mod_count>
        <sys_updated_by>LasBal</sys_updated_by>
        <sys_updated_on>2019-08-26 09:35:50</sys_updated_on>
        <value>(function() {&#13;
	// return the value to use for Parameter 2&#13;
	return "";&#13;
}());</value>
        <variable display_value="">c35dd3ef0a0a0ba96248a70947e35325</variable>
    </sys_variable_value>
    <wf_condition action="INSERT_OR_UPDATE">
        <activity display_value="Notify User, Assignee and User.Manager">8b1a12b0db67b700b26388805b9619a3</activity>
        <condition>true</condition>
        <condition_default/>
        <condition_type>standard</condition_type>
        <else_flag>false</else_flag>
        <error>false</error>
        <event>false</event>
        <event_name/>
        <is_positive>true</is_positive>
        <name>Always</name>
        <order>0</order>
        <short_description/>
        <skip_during_generate>false</skip_during_generate>
        <sys_created_by>LasBal</sys_created_by>
        <sys_created_on>2019-08-26 09:35:50</sys_created_on>
        <sys_id>871a12b0db67b700b26388805b9619a4</sys_id>
        <sys_mod_count>0</sys_mod_count>
        <sys_updated_by>LasBal</sys_updated_by>
        <sys_updated_on>2019-08-26 09:35:50</sys_updated_on>
    </wf_condition>
    <wf_activity action="INSERT_OR_UPDATE">
        <activity_definition display_value="Timer">3961a1da0a0a0b5c00ecd84822f70d85</activity_definition>
        <activity_definition_updated>false</activity_definition_updated>
        <databus_lookup_id>11</databus_lookup_id>
        <height/>
        <input>{}</input>
        <is_parent>false</is_parent>
        <name>Wait 5 working days after 'Error found at'</name>
        <new_activity_definition/>
        <notes/>
        <out_of_date>false</out_of_date>
        <parent/>
        <pinned>false</pinned>
        <pinned_version/>
        <stage/>
        <sys_created_by>LasBal</sys_created_by>
        <sys_created_on>2019-08-26 09:35:50</sys_created_on>
        <sys_id>431a12b0db67b700b26388805b9619a6</sys_id>
        <sys_mod_count>0</sys_mod_count>
        <sys_updated_by>LasBal</sys_updated_by>
        <sys_updated_on>2019-08-26 09:35:50</sys_updated_on>
        <timeout>1970-01-01 00:00:00</timeout>
        <vars/>
        <width/>
        <workflow_version display_value="QC app reminder wf">c31a12b0db67b700b26388805b96199d</workflow_version>
        <x>812</x>
        <y>20</y>
    </wf_activity>
    <sys_variable_value action="delete_multiple" query="document_key=431a12b0db67b700b26388805b9619a6"/>
    <sys_variable_value action="INSERT_OR_UPDATE">
        <document>wf_activity</document>
        <document_key>431a12b0db67b700b26388805b9619a6</document_key>
        <order>310</order>
        <sys_class_name>sys_variable_value</sys_class_name>
        <sys_created_by>LasBal</sys_created_by>
        <sys_created_on>2019-08-26 09:35:50</sys_created_on>
        <sys_id>031a96b0db67b700b26388805b961996</sys_id>
        <sys_mod_count>0</sys_mod_count>
        <sys_updated_by>LasBal</sys_updated_by>
        <sys_updated_on>2019-08-26 09:35:50</sys_updated_on>
        <value>field</value>
        <variable display_value="">21f80cd00a0a0b2101fcd5b5defc0810</variable>
    </sys_variable_value>
    <sys_variable_value action="INSERT_OR_UPDATE">
        <document>wf_activity</document>
        <document_key>431a12b0db67b700b26388805b9619a6</document_key>
        <order>1310</order>
        <sys_class_name>sys_variable_value</sys_class_name>
        <sys_created_by>LasBal</sys_created_by>
        <sys_created_on>2019-08-26 09:35:50</sys_created_on>
        <sys_id>0b1a12b0db67b700b26388805b9619a7</sys_id>
        <sys_mod_count>0</sys_mod_count>
        <sys_updated_by>LasBal</sys_updated_by>
        <sys_updated_on>2019-08-26 09:35:50</sys_updated_on>
        <value>u_error_found_at</value>
        <variable display_value="">21fd462c0a0a0b211c997276d7806c03</variable>
    </sys_variable_value>
    <sys_variable_value action="INSERT_OR_UPDATE">
        <document>wf_activity</document>
        <document_key>431a12b0db67b700b26388805b9619a6</document_key>
        <order>350</order>
        <sys_class_name>sys_variable_value</sys_class_name>
        <sys_created_by>LasBal</sys_created_by>
        <sys_created_on>2019-08-26 09:35:50</sys_created_on>
        <sys_id>0f1a12b0db67b700b26388805b9619a6</sys_id>
        <sys_mod_count>0</sys_mod_count>
        <sys_updated_by>LasBal</sys_updated_by>
        <sys_updated_on>2019-08-26 09:35:50</sys_updated_on>
        <value>user_specified_timezone</value>
        <variable display_value="">4cbfe48a0a0a0b5200cf8b82cc6685f1</variable>
    </sys_variable_value>
    <sys_variable_value action="INSERT_OR_UPDATE">
        <document>wf_activity</document>
        <document_key>431a12b0db67b700b26388805b9619a6</document_key>
        <order>1310</order>
        <sys_class_name>sys_variable_value</sys_class_name>
        <sys_created_by>LasBal</sys_created_by>
        <sys_created_on>2019-08-26 09:35:50</sys_created_on>
        <sys_id>471a12b0db67b700b26388805b9619a7</sys_id>
        <sys_mod_count>0</sys_mod_count>
        <sys_updated_by>LasBal</sys_updated_by>
        <sys_updated_on>2019-08-26 09:35:50</sys_updated_on>
        <value>3bf802c20a0a0b52008e2859cd8abcf2</value>
        <variable display_value="">220cd53d0a0a0b214103bdc2ec5c7ab4</variable>
    </sys_variable_value>
    <sys_variable_value action="INSERT_OR_UPDATE">
        <document>wf_activity</document>
        <document_key>431a12b0db67b700b26388805b9619a6</document_key>
        <order>1350</order>
        <sys_class_name>sys_variable_value</sys_class_name>
        <sys_created_by>LasBal</sys_created_by>
        <sys_created_on>2019-08-26 09:35:50</sys_created_on>
        <sys_id>4b1a12b0db67b700b26388805b9619a6</sys_id>
        <sys_mod_count>0</sys_mod_count>
        <sys_updated_by>LasBal</sys_updated_by>
        <sys_updated_on>2019-08-26 09:35:50</sys_updated_on>
        <value/>
        <variable display_value="">4cc836da0a0a0b520083ebc07da2f47c</variable>
    </sys_variable_value>
    <sys_variable_value action="INSERT_OR_UPDATE">
        <document>wf_activity</document>
        <document_key>431a12b0db67b700b26388805b9619a6</document_key>
        <order>1360</order>
        <sys_class_name>sys_variable_value</sys_class_name>
        <sys_created_by>LasBal</sys_created_by>
        <sys_created_on>2019-08-26 09:35:50</sys_created_on>
        <sys_id>4f1a96b0db67b700b26388805b961995</sys_id>
        <sys_mod_count>0</sys_mod_count>
        <sys_updated_by>LasBal</sys_updated_by>
        <sys_updated_on>2019-08-26 09:35:50</sys_updated_on>
        <value>1970-01-01 00:02:00</value>
        <variable display_value="">292c91070a0a0b212543d91ffde5014c</variable>
    </sys_variable_value>
    <sys_variable_value action="INSERT_OR_UPDATE">
        <document>wf_activity</document>
        <document_key>431a12b0db67b700b26388805b9619a6</document_key>
        <order>1310</order>
        <sys_class_name>sys_variable_value</sys_class_name>
        <sys_created_by>LasBal</sys_created_by>
        <sys_created_on>2019-08-26 09:35:50</sys_created_on>
        <sys_id>831a12b0db67b700b26388805b9619a7</sys_id>
        <sys_mod_count>0</sys_mod_count>
        <sys_updated_by>LasBal</sys_updated_by>
        <sys_updated_on>2019-08-26 09:35:50</sys_updated_on>
        <value/>
        <variable display_value="">c35dc0df0a0a0ba96248a7098d737925</variable>
    </sys_variable_value>
    <sys_variable_value action="INSERT_OR_UPDATE">
        <document>wf_activity</document>
        <document_key>431a12b0db67b700b26388805b9619a6</document_key>
        <order>500</order>
        <sys_class_name>sys_variable_value</sys_class_name>
        <sys_created_by>LasBal</sys_created_by>
        <sys_created_on>2019-08-26 09:35:50</sys_created_on>
        <sys_id>871a12b0db67b700b26388805b9619a6</sys_id>
        <sys_mod_count>0</sys_mod_count>
        <sys_updated_by>LasBal</sys_updated_by>
        <sys_updated_on>2019-08-26 09:35:50</sys_updated_on>
        <value>after</value>
        <variable display_value="">220dc5a40a0a0b2109fbd28b8c4b6213</variable>
    </sys_variable_value>
    <sys_variable_value action="INSERT_OR_UPDATE">
        <document>wf_activity</document>
        <document_key>431a12b0db67b700b26388805b9619a6</document_key>
        <order>1320</order>
        <sys_class_name>sys_variable_value</sys_class_name>
        <sys_created_by>LasBal</sys_created_by>
        <sys_created_on>2019-08-26 09:35:50</sys_created_on>
        <sys_id>8b1a96b0db67b700b26388805b961995</sys_id>
        <sys_mod_count>0</sys_mod_count>
        <sys_updated_by>LasBal</sys_updated_by>
        <sys_updated_on>2019-08-26 09:35:50</sys_updated_on>
        <value/>
        <variable display_value="">4cc6788c0a0a0b5200e6743c94001b16</variable>
    </sys_variable_value>
    <sys_variable_value action="INSERT_OR_UPDATE">
        <document>wf_activity</document>
        <document_key>431a12b0db67b700b26388805b9619a6</document_key>
        <order>1360</order>
        <sys_class_name>sys_variable_value</sys_class_name>
        <sys_created_by>LasBal</sys_created_by>
        <sys_created_on>2019-08-26 09:35:50</sys_created_on>
        <sys_id>8f1a12b0db67b700b26388805b9619a7</sys_id>
        <sys_mod_count>0</sys_mod_count>
        <sys_updated_by>LasBal</sys_updated_by>
        <sys_updated_on>2019-08-26 09:35:50</sys_updated_on>
        <value/>
        <variable display_value="">292b2f0e0a0a0b215aa2dd2cbc578dc5</variable>
    </sys_variable_value>
    <sys_variable_value action="INSERT_OR_UPDATE">
        <document>wf_activity</document>
        <document_key>431a12b0db67b700b26388805b9619a6</document_key>
        <order>320</order>
        <sys_class_name>sys_variable_value</sys_class_name>
        <sys_created_by>LasBal</sys_created_by>
        <sys_created_on>2019-08-26 09:35:50</sys_created_on>
        <sys_id>c31a12b0db67b700b26388805b9619a6</sys_id>
        <sys_mod_count>0</sys_mod_count>
        <sys_updated_by>LasBal</sys_updated_by>
        <sys_updated_on>2019-08-26 09:35:50</sys_updated_on>
        <value>user_specified_schedule</value>
        <variable display_value="">4cba34da0a0a0b5200798c86eafe1203</variable>
    </sys_variable_value>
    <sys_variable_value action="INSERT_OR_UPDATE">
        <document>wf_activity</document>
        <document_key>431a12b0db67b700b26388805b9619a6</document_key>
        <order>1350</order>
        <sys_class_name>sys_variable_value</sys_class_name>
        <sys_created_by>LasBal</sys_created_by>
        <sys_created_on>2019-08-26 09:35:50</sys_created_on>
        <sys_id>c31a96b0db67b700b26388805b961996</sys_id>
        <sys_mod_count>0</sys_mod_count>
        <sys_updated_by>LasBal</sys_updated_by>
        <sys_updated_on>2019-08-26 09:35:50</sys_updated_on>
        <value/>
        <variable display_value="">4cc740fe0a0a0b520025dcf8e2ff78e7</variable>
    </sys_variable_value>
    <sys_variable_value action="INSERT_OR_UPDATE">
        <document>wf_activity</document>
        <document_key>431a12b0db67b700b26388805b9619a6</document_key>
        <order>1320</order>
        <sys_class_name>sys_variable_value</sys_class_name>
        <sys_created_by>LasBal</sys_created_by>
        <sys_created_on>2019-08-26 09:35:50</sys_created_on>
        <sys_id>c71a96b0db67b700b26388805b961995</sys_id>
        <sys_mod_count>0</sys_mod_count>
        <sys_updated_by>LasBal</sys_updated_by>
        <sys_updated_on>2019-08-26 09:35:50</sys_updated_on>
        <value>fef684a3dbdf1b00b26388805b9619ec</value>
        <variable display_value="">4cc4a4030a0a0b52007334f001376dc5</variable>
    </sys_variable_value>
    <sys_variable_value action="INSERT_OR_UPDATE">
        <document>wf_activity</document>
        <document_key>431a12b0db67b700b26388805b9619a6</document_key>
        <order>1360</order>
        <sys_class_name>sys_variable_value</sys_class_name>
        <sys_created_by>LasBal</sys_created_by>
        <sys_created_on>2019-08-26 09:35:50</sys_created_on>
        <sys_id>cb1a12b0db67b700b26388805b9619a7</sys_id>
        <sys_mod_count>0</sys_mod_count>
        <sys_updated_by>LasBal</sys_updated_by>
        <sys_updated_on>2019-08-26 09:35:50</sys_updated_on>
        <value/>
        <variable display_value="">292bd15e0a0a0b215a040c701033e3c5</variable>
    </sys_variable_value>
    <sys_variable_value action="INSERT_OR_UPDATE">
        <document>wf_activity</document>
        <document_key>431a12b0db67b700b26388805b9619a6</document_key>
        <order>3000</order>
        <sys_class_name>sys_variable_value</sys_class_name>
        <sys_created_by>LasBal</sys_created_by>
        <sys_created_on>2019-08-26 09:35:50</sys_created_on>
        <sys_id>cf1a12b0db67b700b26388805b9619a6</sys_id>
        <sys_mod_count>0</sys_mod_count>
        <sys_updated_by>LasBal</sys_updated_by>
        <sys_updated_on>2019-08-26 09:35:50</sys_updated_on>
        <value>// Set 'answer' to the number of seconds this timer should wait&#13;
answer = 0;</value>
        <variable display_value="">293493710a0a0b2115e3e5b4fce1d12a</variable>
    </sys_variable_value>
    <sys_variable_value action="INSERT_OR_UPDATE">
        <document>wf_activity</document>
        <document_key>431a12b0db67b700b26388805b9619a6</document_key>
        <order>310</order>
        <sys_class_name>sys_variable_value</sys_class_name>
        <sys_created_by>LasBal</sys_created_by>
        <sys_created_on>2019-08-26 09:35:50</sys_created_on>
        <sys_id>031a96b0db67b700b26388805b961996</sys_id>
        <sys_mod_count>0</sys_mod_count>
        <sys_updated_by>LasBal</sys_updated_by>
        <sys_updated_on>2019-08-26 09:35:50</sys_updated_on>
        <value>field</value>
        <variable display_value="">21f80cd00a0a0b2101fcd5b5defc0810</variable>
    </sys_variable_value>
    <sys_variable_value action="INSERT_OR_UPDATE">
        <document>wf_activity</document>
        <document_key>431a12b0db67b700b26388805b9619a6</document_key>
        <order>320</order>
        <sys_class_name>sys_variable_value</sys_class_name>
        <sys_created_by>LasBal</sys_created_by>
        <sys_created_on>2019-08-26 09:35:50</sys_created_on>
        <sys_id>c31a12b0db67b700b26388805b9619a6</sys_id>
        <sys_mod_count>0</sys_mod_count>
        <sys_updated_by>LasBal</sys_updated_by>
        <sys_updated_on>2019-08-26 09:35:50</sys_updated_on>
        <value>user_specified_schedule</value>
        <variable display_value="">4cba34da0a0a0b5200798c86eafe1203</variable>
    </sys_variable_value>
    <sys_variable_value action="INSERT_OR_UPDATE">
        <document>wf_activity</document>
        <document_key>431a12b0db67b700b26388805b9619a6</document_key>
        <order>350</order>
        <sys_class_name>sys_variable_value</sys_class_name>
        <sys_created_by>LasBal</sys_created_by>
        <sys_created_on>2019-08-26 09:35:50</sys_created_on>
        <sys_id>0f1a12b0db67b700b26388805b9619a6</sys_id>
        <sys_mod_count>0</sys_mod_count>
        <sys_updated_by>LasBal</sys_updated_by>
        <sys_updated_on>2019-08-26 09:35:50</sys_updated_on>
        <value>user_specified_timezone</value>
        <variable display_value="">4cbfe48a0a0a0b5200cf8b82cc6685f1</variable>
    </sys_variable_value>
    <sys_variable_value action="INSERT_OR_UPDATE">
        <document>wf_activity</document>
        <document_key>431a12b0db67b700b26388805b9619a6</document_key>
        <order>500</order>
        <sys_class_name>sys_variable_value</sys_class_name>
        <sys_created_by>LasBal</sys_created_by>
        <sys_created_on>2019-08-26 09:35:50</sys_created_on>
        <sys_id>871a12b0db67b700b26388805b9619a6</sys_id>
        <sys_mod_count>0</sys_mod_count>
        <sys_updated_by>LasBal</sys_updated_by>
        <sys_updated_on>2019-08-26 09:35:50</sys_updated_on>
        <value>after</value>
        <variable display_value="">220dc5a40a0a0b2109fbd28b8c4b6213</variable>
    </sys_variable_value>
    <sys_variable_value action="INSERT_OR_UPDATE">
        <document>wf_activity</document>
        <document_key>431a12b0db67b700b26388805b9619a6</document_key>
        <order>1310</order>
        <sys_class_name>sys_variable_value</sys_class_name>
        <sys_created_by>LasBal</sys_created_by>
        <sys_created_on>2019-08-26 09:35:50</sys_created_on>
        <sys_id>831a12b0db67b700b26388805b9619a7</sys_id>
        <sys_mod_count>0</sys_mod_count>
        <sys_updated_by>LasBal</sys_updated_by>
        <sys_updated_on>2019-08-26 09:35:50</sys_updated_on>
        <value/>
        <variable display_value="">c35dc0df0a0a0ba96248a7098d737925</variable>
    </sys_variable_value>
    <sys_variable_value action="INSERT_OR_UPDATE">
        <document>wf_activity</document>
        <document_key>431a12b0db67b700b26388805b9619a6</document_key>
        <order>1310</order>
        <sys_class_name>sys_variable_value</sys_class_name>
        <sys_created_by>LasBal</sys_created_by>
        <sys_created_on>2019-08-26 09:35:50</sys_created_on>
        <sys_id>471a12b0db67b700b26388805b9619a7</sys_id>
        <sys_mod_count>0</sys_mod_count>
        <sys_updated_by>LasBal</sys_updated_by>
        <sys_updated_on>2019-08-26 09:35:50</sys_updated_on>
        <value>3bf802c20a0a0b52008e2859cd8abcf2</value>
        <variable display_value="">220cd53d0a0a0b214103bdc2ec5c7ab4</variable>
    </sys_variable_value>
    <sys_variable_value action="INSERT_OR_UPDATE">
        <document>wf_activity</document>
        <document_key>431a12b0db67b700b26388805b9619a6</document_key>
        <order>1310</order>
        <sys_class_name>sys_variable_value</sys_class_name>
        <sys_created_by>LasBal</sys_created_by>
        <sys_created_on>2019-08-26 09:35:50</sys_created_on>
        <sys_id>0b1a12b0db67b700b26388805b9619a7</sys_id>
        <sys_mod_count>0</sys_mod_count>
        <sys_updated_by>LasBal</sys_updated_by>
        <sys_updated_on>2019-08-26 09:35:50</sys_updated_on>
        <value>u_error_found_at</value>
        <variable display_value="">21fd462c0a0a0b211c997276d7806c03</variable>
    </sys_variable_value>
    <sys_variable_value action="INSERT_OR_UPDATE">
        <document>wf_activity</document>
        <document_key>431a12b0db67b700b26388805b9619a6</document_key>
        <order>1320</order>
        <sys_class_name>sys_variable_value</sys_class_name>
        <sys_created_by>LasBal</sys_created_by>
        <sys_created_on>2019-08-26 09:35:50</sys_created_on>
        <sys_id>8b1a96b0db67b700b26388805b961995</sys_id>
        <sys_mod_count>0</sys_mod_count>
        <sys_updated_by>LasBal</sys_updated_by>
        <sys_updated_on>2019-08-26 09:35:50</sys_updated_on>
        <value/>
        <variable display_value="">4cc6788c0a0a0b5200e6743c94001b16</variable>
    </sys_variable_value>
    <sys_variable_value action="INSERT_OR_UPDATE">
        <document>wf_activity</document>
        <document_key>431a12b0db67b700b26388805b9619a6</document_key>
        <order>1320</order>
        <sys_class_name>sys_variable_value</sys_class_name>
        <sys_created_by>LasBal</sys_created_by>
        <sys_created_on>2019-08-26 09:35:50</sys_created_on>
        <sys_id>c71a96b0db67b700b26388805b961995</sys_id>
        <sys_mod_count>0</sys_mod_count>
        <sys_updated_by>LasBal</sys_updated_by>
        <sys_updated_on>2019-08-26 09:35:50</sys_updated_on>
        <value>fef684a3dbdf1b00b26388805b9619ec</value>
        <variable display_value="">4cc4a4030a0a0b52007334f001376dc5</variable>
    </sys_variable_value>
    <sys_variable_value action="INSERT_OR_UPDATE">
        <document>wf_activity</document>
        <document_key>431a12b0db67b700b26388805b9619a6</document_key>
        <order>1350</order>
        <sys_class_name>sys_variable_value</sys_class_name>
        <sys_created_by>LasBal</sys_created_by>
        <sys_created_on>2019-08-26 09:35:50</sys_created_on>
        <sys_id>4b1a12b0db67b700b26388805b9619a6</sys_id>
        <sys_mod_count>0</sys_mod_count>
        <sys_updated_by>LasBal</sys_updated_by>
        <sys_updated_on>2019-08-26 09:35:50</sys_updated_on>
        <value/>
        <variable display_value="">4cc836da0a0a0b520083ebc07da2f47c</variable>
    </sys_variable_value>
    <sys_variable_value action="INSERT_OR_UPDATE">
        <document>wf_activity</document>
        <document_key>431a12b0db67b700b26388805b9619a6</document_key>
        <order>1350</order>
        <sys_class_name>sys_variable_value</sys_class_name>
        <sys_created_by>LasBal</sys_created_by>
        <sys_created_on>2019-08-26 09:35:50</sys_created_on>
        <sys_id>c31a96b0db67b700b26388805b961996</sys_id>
        <sys_mod_count>0</sys_mod_count>
        <sys_updated_by>LasBal</sys_updated_by>
        <sys_updated_on>2019-08-26 09:35:50</sys_updated_on>
        <value/>
        <variable display_value="">4cc740fe0a0a0b520025dcf8e2ff78e7</variable>
    </sys_variable_value>
    <sys_variable_value action="INSERT_OR_UPDATE">
        <document>wf_activity</document>
        <document_key>431a12b0db67b700b26388805b9619a6</document_key>
        <order>1360</order>
        <sys_class_name>sys_variable_value</sys_class_name>
        <sys_created_by>LasBal</sys_created_by>
        <sys_created_on>2019-08-26 09:35:50</sys_created_on>
        <sys_id>cb1a12b0db67b700b26388805b9619a7</sys_id>
        <sys_mod_count>0</sys_mod_count>
        <sys_updated_by>LasBal</sys_updated_by>
        <sys_updated_on>2019-08-26 09:35:50</sys_updated_on>
        <value/>
        <variable display_value="">292bd15e0a0a0b215a040c701033e3c5</variable>
    </sys_variable_value>
    <sys_variable_value action="INSERT_OR_UPDATE">
        <document>wf_activity</document>
        <document_key>431a12b0db67b700b26388805b9619a6</document_key>
        <order>1360</order>
        <sys_class_name>sys_variable_value</sys_class_name>
        <sys_created_by>LasBal</sys_created_by>
        <sys_created_on>2019-08-26 09:35:50</sys_created_on>
        <sys_id>8f1a12b0db67b700b26388805b9619a7</sys_id>
        <sys_mod_count>0</sys_mod_count>
        <sys_updated_by>LasBal</sys_updated_by>
        <sys_updated_on>2019-08-26 09:35:50</sys_updated_on>
        <value/>
        <variable display_value="">292b2f0e0a0a0b215aa2dd2cbc578dc5</variable>
    </sys_variable_value>
    <sys_variable_value action="INSERT_OR_UPDATE">
        <document>wf_activity</document>
        <document_key>431a12b0db67b700b26388805b9619a6</document_key>
        <order>1360</order>
        <sys_class_name>sys_variable_value</sys_class_name>
        <sys_created_by>LasBal</sys_created_by>
        <sys_created_on>2019-08-26 09:35:50</sys_created_on>
        <sys_id>4f1a96b0db67b700b26388805b961995</sys_id>
        <sys_mod_count>0</sys_mod_count>
        <sys_updated_by>LasBal</sys_updated_by>
        <sys_updated_on>2019-08-26 09:35:50</sys_updated_on>
        <value>1970-01-01 00:02:00</value>
        <variable display_value="">292c91070a0a0b212543d91ffde5014c</variable>
    </sys_variable_value>
    <sys_variable_value action="INSERT_OR_UPDATE">
        <document>wf_activity</document>
        <document_key>431a12b0db67b700b26388805b9619a6</document_key>
        <order>3000</order>
        <sys_class_name>sys_variable_value</sys_class_name>
        <sys_created_by>LasBal</sys_created_by>
        <sys_created_on>2019-08-26 09:35:50</sys_created_on>
        <sys_id>cf1a12b0db67b700b26388805b9619a6</sys_id>
        <sys_mod_count>0</sys_mod_count>
        <sys_updated_by>LasBal</sys_updated_by>
        <sys_updated_on>2019-08-26 09:35:50</sys_updated_on>
        <value>// Set 'answer' to the number of seconds this timer should wait&#13;
answer = 0;</value>
        <variable display_value="">293493710a0a0b2115e3e5b4fce1d12a</variable>
    </sys_variable_value>
    <wf_condition action="INSERT_OR_UPDATE">
        <activity display_value="Wait 5 working days after 'Error found at'">431a12b0db67b700b26388805b9619a6</activity>
        <condition>activity.result != 'repair'</condition>
        <condition_default/>
        <condition_type>standard</condition_type>
        <else_flag>false</else_flag>
        <error>false</error>
        <event>false</event>
        <event_name/>
        <is_positive>false</is_positive>
        <name>Normal</name>
        <order>0</order>
        <short_description>The SLA is running normally (not being repaired)</short_description>
        <skip_during_generate>false</skip_during_generate>
        <sys_created_by>LasBal</sys_created_by>
        <sys_created_on>2019-08-26 09:35:50</sys_created_on>
        <sys_id>4b1a96b0db67b700b26388805b961996</sys_id>
        <sys_mod_count>0</sys_mod_count>
        <sys_updated_by>LasBal</sys_updated_by>
        <sys_updated_on>2019-08-26 09:35:50</sys_updated_on>
    </wf_condition>
    <wf_condition action="INSERT_OR_UPDATE">
        <activity display_value="Wait 5 working days after 'Error found at'">431a12b0db67b700b26388805b9619a6</activity>
        <condition>activity.result == 'repair'</condition>
        <condition_default/>
        <condition_type>standard</condition_type>
        <else_flag>false</else_flag>
        <error>false</error>
        <event>false</event>
        <event_name/>
        <is_positive>false</is_positive>
        <name>Repair</name>
        <order>0</order>
        <short_description>The SLA is being repaired</short_description>
        <skip_during_generate>false</skip_during_generate>
        <sys_created_by>LasBal</sys_created_by>
        <sys_created_on>2019-08-26 09:35:50</sys_created_on>
        <sys_id>c71a96b0db67b700b26388805b961996</sys_id>
        <sys_mod_count>0</sys_mod_count>
        <sys_updated_by>LasBal</sys_updated_by>
        <sys_updated_on>2019-08-26 09:35:50</sys_updated_on>
    </wf_condition>
    <wf_activity action="INSERT_OR_UPDATE">
        <activity_definition display_value="Join">7c9a2ba9c0a801650021ada408de0ebd</activity_definition>
        <activity_definition_updated>false</activity_definition_updated>
        <databus_lookup_id/>
        <height/>
        <input/>
        <is_parent>false</is_parent>
        <name>Wait for all activities to complete</name>
        <new_activity_definition/>
        <notes/>
        <out_of_date>false</out_of_date>
        <parent/>
        <pinned>false</pinned>
        <pinned_version/>
        <stage/>
        <sys_created_by>LasBal</sys_created_by>
        <sys_created_on>2019-08-26 09:35:50</sys_created_on>
        <sys_id>0f1a12b0db67b700b26388805b9619a4</sys_id>
        <sys_mod_count>0</sys_mod_count>
        <sys_updated_by>LasBal</sys_updated_by>
        <sys_updated_on>2019-08-26 09:35:50</sys_updated_on>
        <timeout>1970-01-01 00:00:00</timeout>
        <vars/>
        <width/>
        <workflow_version display_value="QC app reminder wf">c31a12b0db67b700b26388805b96199d</workflow_version>
        <x>464</x>
        <y>546</y>
    </wf_activity>
    <sys_variable_value action="delete_multiple" query="document_key=0f1a12b0db67b700b26388805b9619a4"/>
    <wf_condition action="INSERT_OR_UPDATE">
        <activity display_value="Wait for all activities to complete">0f1a12b0db67b700b26388805b9619a4</activity>
        <condition>activity.result == 'complete'</condition>
        <condition_default/>
        <condition_type>standard</condition_type>
        <else_flag>false</else_flag>
        <error>false</error>
        <event>false</event>
        <event_name/>
        <is_positive>false</is_positive>
        <name>Complete</name>
        <order>1</order>
        <short_description>All predecessor activities have transitioned to this activity</short_description>
        <skip_during_generate>false</skip_during_generate>
        <sys_created_by>LasBal</sys_created_by>
        <sys_created_on>2019-08-26 09:35:50</sys_created_on>
        <sys_id>431a12b0db67b700b26388805b9619a5</sys_id>
        <sys_mod_count>0</sys_mod_count>
        <sys_updated_by>LasBal</sys_updated_by>
        <sys_updated_on>2019-08-26 09:35:50</sys_updated_on>
    </wf_condition>
    <wf_condition action="INSERT_OR_UPDATE">
        <activity display_value="Wait for all activities to complete">0f1a12b0db67b700b26388805b9619a4</activity>
        <condition>activity.result == 'incomplete'</condition>
        <condition_default/>
        <condition_type>standard</condition_type>
        <else_flag>false</else_flag>
        <error>false</error>
        <event>false</event>
        <event_name/>
        <is_positive>false</is_positive>
        <name>Incomplete</name>
        <order>2</order>
        <short_description>At least one predecessor activities did not transition to this activity</short_description>
        <skip_during_generate>true</skip_during_generate>
        <sys_created_by>LasBal</sys_created_by>
        <sys_created_on>2019-08-26 09:35:50</sys_created_on>
        <sys_id>cf1a12b0db67b700b26388805b9619a4</sys_id>
        <sys_mod_count>0</sys_mod_count>
        <sys_updated_by>LasBal</sys_updated_by>
        <sys_updated_on>2019-08-26 09:35:50</sys_updated_on>
    </wf_condition>
    <wf_activity action="INSERT_OR_UPDATE">
        <activity_definition display_value="Timer">3961a1da0a0a0b5c00ecd84822f70d85</activity_definition>
        <activity_definition_updated>false</activity_definition_updated>
        <databus_lookup_id>10</databus_lookup_id>
        <height/>
        <input>{}</input>
        <is_parent>false</is_parent>
        <name>Wait until 2 days after 'Error found at'</name>
        <new_activity_definition/>
        <notes/>
        <out_of_date>false</out_of_date>
        <parent/>
        <pinned>false</pinned>
        <pinned_version/>
        <stage/>
        <sys_created_by>LasBal</sys_created_by>
        <sys_created_on>2019-08-26 09:35:49</sys_created_on>
        <sys_id>4b1a12b0db67b700b26388805b96199e</sys_id>
        <sys_mod_count>0</sys_mod_count>
        <sys_updated_by>LasBal</sys_updated_by>
        <sys_updated_on>2019-08-26 09:35:49</sys_updated_on>
        <timeout>1970-01-01 00:00:00</timeout>
        <vars/>
        <width/>
        <workflow_version display_value="QC app reminder wf">c31a12b0db67b700b26388805b96199d</workflow_version>
        <x>273</x>
        <y>52</y>
    </wf_activity>
    <sys_variable_value action="delete_multiple" query="document_key=4b1a12b0db67b700b26388805b96199e"/>
    <sys_variable_value action="INSERT_OR_UPDATE">
        <document>wf_activity</document>
        <document_key>4b1a12b0db67b700b26388805b96199e</document_key>
        <order>1310</order>
        <sys_class_name>sys_variable_value</sys_class_name>
        <sys_created_by>LasBal</sys_created_by>
        <sys_created_on>2019-08-26 09:35:49</sys_created_on>
        <sys_id>031a12b0db67b700b26388805b9619a0</sys_id>
        <sys_mod_count>0</sys_mod_count>
        <sys_updated_by>LasBal</sys_updated_by>
        <sys_updated_on>2019-08-26 09:35:49</sys_updated_on>
        <value>3bf802c20a0a0b52008e2859cd8abcf2</value>
        <variable display_value="">220cd53d0a0a0b214103bdc2ec5c7ab4</variable>
    </sys_variable_value>
    <sys_variable_value action="INSERT_OR_UPDATE">
        <document>wf_activity</document>
        <document_key>4b1a12b0db67b700b26388805b96199e</document_key>
        <order>1350</order>
        <sys_class_name>sys_variable_value</sys_class_name>
        <sys_created_by>LasBal</sys_created_by>
        <sys_created_on>2019-08-26 09:35:49</sys_created_on>
        <sys_id>071a12b0db67b700b26388805b96199f</sys_id>
        <sys_mod_count>0</sys_mod_count>
        <sys_updated_by>LasBal</sys_updated_by>
        <sys_updated_on>2019-08-26 09:35:49</sys_updated_on>
        <value/>
        <variable display_value="">4cc836da0a0a0b520083ebc07da2f47c</variable>
    </sys_variable_value>
    <sys_variable_value action="INSERT_OR_UPDATE">
        <document>wf_activity</document>
        <document_key>4b1a12b0db67b700b26388805b96199e</document_key>
        <order>1350</order>
        <sys_class_name>sys_variable_value</sys_class_name>
        <sys_created_by>LasBal</sys_created_by>
        <sys_created_on>2019-08-26 09:35:49</sys_created_on>
        <sys_id>0b1a12b0db67b700b26388805b9619a1</sys_id>
        <sys_mod_count>0</sys_mod_count>
        <sys_updated_by>LasBal</sys_updated_by>
        <sys_updated_on>2019-08-26 09:35:49</sys_updated_on>
        <value/>
        <variable display_value="">4cc740fe0a0a0b520025dcf8e2ff78e7</variable>
    </sys_variable_value>
    <sys_variable_value action="INSERT_OR_UPDATE">
        <document>wf_activity</document>
        <document_key>4b1a12b0db67b700b26388805b96199e</document_key>
        <order>1320</order>
        <sys_class_name>sys_variable_value</sys_class_name>
        <sys_created_by>LasBal</sys_created_by>
        <sys_created_on>2019-08-26 09:35:49</sys_created_on>
        <sys_id>0f1a12b0db67b700b26388805b9619a0</sys_id>
        <sys_mod_count>0</sys_mod_count>
        <sys_updated_by>LasBal</sys_updated_by>
        <sys_updated_on>2019-08-26 09:35:49</sys_updated_on>
        <value>fef684a3dbdf1b00b26388805b9619ec</value>
        <variable display_value="">4cc4a4030a0a0b52007334f001376dc5</variable>
    </sys_variable_value>
    <sys_variable_value action="INSERT_OR_UPDATE">
        <document>wf_activity</document>
        <document_key>4b1a12b0db67b700b26388805b96199e</document_key>
        <order>500</order>
        <sys_class_name>sys_variable_value</sys_class_name>
        <sys_created_by>LasBal</sys_created_by>
        <sys_created_on>2019-08-26 09:35:49</sys_created_on>
        <sys_id>431a12b0db67b700b26388805b96199f</sys_id>
        <sys_mod_count>0</sys_mod_count>
        <sys_updated_by>LasBal</sys_updated_by>
        <sys_updated_on>2019-08-26 09:35:49</sys_updated_on>
        <value>after</value>
        <variable display_value="">220dc5a40a0a0b2109fbd28b8c4b6213</variable>
    </sys_variable_value>
    <sys_variable_value action="INSERT_OR_UPDATE">
        <document>wf_activity</document>
        <document_key>4b1a12b0db67b700b26388805b96199e</document_key>
        <order>310</order>
        <sys_class_name>sys_variable_value</sys_class_name>
        <sys_created_by>LasBal</sys_created_by>
        <sys_created_on>2019-08-26 09:35:49</sys_created_on>
        <sys_id>471a12b0db67b700b26388805b9619a1</sys_id>
        <sys_mod_count>0</sys_mod_count>
        <sys_updated_by>LasBal</sys_updated_by>
        <sys_updated_on>2019-08-26 09:35:49</sys_updated_on>
        <value>field</value>
        <variable display_value="">21f80cd00a0a0b2101fcd5b5defc0810</variable>
    </sys_variable_value>
    <sys_variable_value action="INSERT_OR_UPDATE">
        <document>wf_activity</document>
        <document_key>4b1a12b0db67b700b26388805b96199e</document_key>
        <order>1360</order>
        <sys_class_name>sys_variable_value</sys_class_name>
        <sys_created_by>LasBal</sys_created_by>
        <sys_created_on>2019-08-26 09:35:49</sys_created_on>
        <sys_id>4b1a12b0db67b700b26388805b9619a0</sys_id>
        <sys_mod_count>0</sys_mod_count>
        <sys_updated_by>LasBal</sys_updated_by>
        <sys_updated_on>2019-08-26 09:35:49</sys_updated_on>
        <value/>
        <variable display_value="">292b2f0e0a0a0b215aa2dd2cbc578dc5</variable>
    </sys_variable_value>
    <sys_variable_value action="INSERT_OR_UPDATE">
        <document>wf_activity</document>
        <document_key>4b1a12b0db67b700b26388805b96199e</document_key>
        <order>320</order>
        <sys_class_name>sys_variable_value</sys_class_name>
        <sys_created_by>LasBal</sys_created_by>
        <sys_created_on>2019-08-26 09:35:49</sys_created_on>
        <sys_id>4f1a12b0db67b700b26388805b96199e</sys_id>
        <sys_mod_count>0</sys_mod_count>
        <sys_updated_by>LasBal</sys_updated_by>
        <sys_updated_on>2019-08-26 09:35:49</sys_updated_on>
        <value>user_specified_schedule</value>
        <variable display_value="">4cba34da0a0a0b5200798c86eafe1203</variable>
    </sys_variable_value>
    <sys_variable_value action="INSERT_OR_UPDATE">
        <document>wf_activity</document>
        <document_key>4b1a12b0db67b700b26388805b96199e</document_key>
        <order>1310</order>
        <sys_class_name>sys_variable_value</sys_class_name>
        <sys_created_by>LasBal</sys_created_by>
        <sys_created_on>2019-08-26 09:35:49</sys_created_on>
        <sys_id>4f1a12b0db67b700b26388805b96199f</sys_id>
        <sys_mod_count>0</sys_mod_count>
        <sys_updated_by>LasBal</sys_updated_by>
        <sys_updated_on>2019-08-26 09:35:49</sys_updated_on>
        <value/>
        <variable display_value="">c35dc0df0a0a0ba96248a7098d737925</variable>
    </sys_variable_value>
    <sys_variable_value action="INSERT_OR_UPDATE">
        <document>wf_activity</document>
        <document_key>4b1a12b0db67b700b26388805b96199e</document_key>
        <order>1360</order>
        <sys_class_name>sys_variable_value</sys_class_name>
        <sys_created_by>LasBal</sys_created_by>
        <sys_created_on>2019-08-26 09:35:49</sys_created_on>
        <sys_id>831a12b0db67b700b26388805b9619a1</sys_id>
        <sys_mod_count>0</sys_mod_count>
        <sys_updated_by>LasBal</sys_updated_by>
        <sys_updated_on>2019-08-26 09:35:49</sys_updated_on>
        <value>1970-01-01 00:01:00</value>
        <variable display_value="">292c91070a0a0b212543d91ffde5014c</variable>
    </sys_variable_value>
    <sys_variable_value action="INSERT_OR_UPDATE">
        <document>wf_activity</document>
        <document_key>4b1a12b0db67b700b26388805b96199e</document_key>
        <order>1360</order>
        <sys_class_name>sys_variable_value</sys_class_name>
        <sys_created_by>LasBal</sys_created_by>
        <sys_created_on>2019-08-26 09:35:49</sys_created_on>
        <sys_id>871a12b0db67b700b26388805b9619a0</sys_id>
        <sys_mod_count>0</sys_mod_count>
        <sys_updated_by>LasBal</sys_updated_by>
        <sys_updated_on>2019-08-26 09:35:49</sys_updated_on>
        <value>1970-01-01 16:00:00</value>
        <variable display_value="">292bd15e0a0a0b215a040c701033e3c5</variable>
    </sys_variable_value>
    <sys_variable_value action="INSERT_OR_UPDATE">
        <document>wf_activity</document>
        <document_key>4b1a12b0db67b700b26388805b96199e</document_key>
        <order>3000</order>
        <sys_class_name>sys_variable_value</sys_class_name>
        <sys_created_by>LasBal</sys_created_by>
        <sys_created_on>2019-08-26 09:35:49</sys_created_on>
        <sys_id>8b1a12b0db67b700b26388805b96199f</sys_id>
        <sys_mod_count>0</sys_mod_count>
        <sys_updated_by>LasBal</sys_updated_by>
        <sys_updated_on>2019-08-26 09:35:49</sys_updated_on>
        <value>// Set 'answer' to the number of seconds this timer should wait&#13;
answer = 0;</value>
        <variable display_value="">293493710a0a0b2115e3e5b4fce1d12a</variable>
    </sys_variable_value>
    <sys_variable_value action="INSERT_OR_UPDATE">
        <document>wf_activity</document>
        <document_key>4b1a12b0db67b700b26388805b96199e</document_key>
        <order>1310</order>
        <sys_class_name>sys_variable_value</sys_class_name>
        <sys_created_by>LasBal</sys_created_by>
        <sys_created_on>2019-08-26 09:35:49</sys_created_on>
        <sys_id>c31a12b0db67b700b26388805b9619a0</sys_id>
        <sys_mod_count>0</sys_mod_count>
        <sys_updated_by>LasBal</sys_updated_by>
        <sys_updated_on>2019-08-26 09:35:49</sys_updated_on>
        <value>u_error_found_at</value>
        <variable display_value="">21fd462c0a0a0b211c997276d7806c03</variable>
    </sys_variable_value>
    <sys_variable_value action="INSERT_OR_UPDATE">
        <document>wf_activity</document>
        <document_key>4b1a12b0db67b700b26388805b96199e</document_key>
        <order>350</order>
        <sys_class_name>sys_variable_value</sys_class_name>
        <sys_created_by>LasBal</sys_created_by>
        <sys_created_on>2019-08-26 09:35:49</sys_created_on>
        <sys_id>c71a12b0db67b700b26388805b96199f</sys_id>
        <sys_mod_count>0</sys_mod_count>
        <sys_updated_by>LasBal</sys_updated_by>
        <sys_updated_on>2019-08-26 09:35:49</sys_updated_on>
        <value>user_specified_timezone</value>
        <variable display_value="">4cbfe48a0a0a0b5200cf8b82cc6685f1</variable>
    </sys_variable_value>
    <sys_variable_value action="INSERT_OR_UPDATE">
        <document>wf_activity</document>
        <document_key>4b1a12b0db67b700b26388805b96199e</document_key>
        <order>1320</order>
        <sys_class_name>sys_variable_value</sys_class_name>
        <sys_created_by>LasBal</sys_created_by>
        <sys_created_on>2019-08-26 09:35:49</sys_created_on>
        <sys_id>cf1a12b0db67b700b26388805b9619a0</sys_id>
        <sys_mod_count>0</sys_mod_count>
        <sys_updated_by>LasBal</sys_updated_by>
        <sys_updated_on>2019-08-26 09:35:49</sys_updated_on>
        <value/>
        <variable display_value="">4cc6788c0a0a0b5200e6743c94001b16</variable>
    </sys_variable_value>
    <sys_variable_value action="INSERT_OR_UPDATE">
        <document>wf_activity</document>
        <document_key>4b1a12b0db67b700b26388805b96199e</document_key>
        <order>310</order>
        <sys_class_name>sys_variable_value</sys_class_name>
        <sys_created_by>LasBal</sys_created_by>
        <sys_created_on>2019-08-26 09:35:49</sys_created_on>
        <sys_id>471a12b0db67b700b26388805b9619a1</sys_id>
        <sys_mod_count>0</sys_mod_count>
        <sys_updated_by>LasBal</sys_updated_by>
        <sys_updated_on>2019-08-26 09:35:49</sys_updated_on>
        <value>field</value>
        <variable display_value="">21f80cd00a0a0b2101fcd5b5defc0810</variable>
    </sys_variable_value>
    <sys_variable_value action="INSERT_OR_UPDATE">
        <document>wf_activity</document>
        <document_key>4b1a12b0db67b700b26388805b96199e</document_key>
        <order>320</order>
        <sys_class_name>sys_variable_value</sys_class_name>
        <sys_created_by>LasBal</sys_created_by>
        <sys_created_on>2019-08-26 09:35:49</sys_created_on>
        <sys_id>4f1a12b0db67b700b26388805b96199e</sys_id>
        <sys_mod_count>0</sys_mod_count>
        <sys_updated_by>LasBal</sys_updated_by>
        <sys_updated_on>2019-08-26 09:35:49</sys_updated_on>
        <value>user_specified_schedule</value>
        <variable display_value="">4cba34da0a0a0b5200798c86eafe1203</variable>
    </sys_variable_value>
    <sys_variable_value action="INSERT_OR_UPDATE">
        <document>wf_activity</document>
        <document_key>4b1a12b0db67b700b26388805b96199e</document_key>
        <order>350</order>
        <sys_class_name>sys_variable_value</sys_class_name>
        <sys_created_by>LasBal</sys_created_by>
        <sys_created_on>2019-08-26 09:35:49</sys_created_on>
        <sys_id>c71a12b0db67b700b26388805b96199f</sys_id>
        <sys_mod_count>0</sys_mod_count>
        <sys_updated_by>LasBal</sys_updated_by>
        <sys_updated_on>2019-08-26 09:35:49</sys_updated_on>
        <value>user_specified_timezone</value>
        <variable display_value="">4cbfe48a0a0a0b5200cf8b82cc6685f1</variable>
    </sys_variable_value>
    <sys_variable_value action="INSERT_OR_UPDATE">
        <document>wf_activity</document>
        <document_key>4b1a12b0db67b700b26388805b96199e</document_key>
        <order>500</order>
        <sys_class_name>sys_variable_value</sys_class_name>
        <sys_created_by>LasBal</sys_created_by>
        <sys_created_on>2019-08-26 09:35:49</sys_created_on>
        <sys_id>431a12b0db67b700b26388805b96199f</sys_id>
        <sys_mod_count>0</sys_mod_count>
        <sys_updated_by>LasBal</sys_updated_by>
        <sys_updated_on>2019-08-26 09:35:49</sys_updated_on>
        <value>after</value>
        <variable display_value="">220dc5a40a0a0b2109fbd28b8c4b6213</variable>
    </sys_variable_value>
    <sys_variable_value action="INSERT_OR_UPDATE">
        <document>wf_activity</document>
        <document_key>4b1a12b0db67b700b26388805b96199e</document_key>
        <order>1310</order>
        <sys_class_name>sys_variable_value</sys_class_name>
        <sys_created_by>LasBal</sys_created_by>
        <sys_created_on>2019-08-26 09:35:49</sys_created_on>
        <sys_id>c31a12b0db67b700b26388805b9619a0</sys_id>
        <sys_mod_count>0</sys_mod_count>
        <sys_updated_by>LasBal</sys_updated_by>
        <sys_updated_on>2019-08-26 09:35:49</sys_updated_on>
        <value>u_error_found_at</value>
        <variable display_value="">21fd462c0a0a0b211c997276d7806c03</variable>
    </sys_variable_value>
    <sys_variable_value action="INSERT_OR_UPDATE">
        <document>wf_activity</document>
        <document_key>4b1a12b0db67b700b26388805b96199e</document_key>
        <order>1310</order>
        <sys_class_name>sys_variable_value</sys_class_name>
        <sys_created_by>LasBal</sys_created_by>
        <sys_created_on>2019-08-26 09:35:49</sys_created_on>
        <sys_id>4f1a12b0db67b700b26388805b96199f</sys_id>
        <sys_mod_count>0</sys_mod_count>
        <sys_updated_by>LasBal</sys_updated_by>
        <sys_updated_on>2019-08-26 09:35:49</sys_updated_on>
        <value/>
        <variable display_value="">c35dc0df0a0a0ba96248a7098d737925</variable>
    </sys_variable_value>
    <sys_variable_value action="INSERT_OR_UPDATE">
        <document>wf_activity</document>
        <document_key>4b1a12b0db67b700b26388805b96199e</document_key>
        <order>1310</order>
        <sys_class_name>sys_variable_value</sys_class_name>
        <sys_created_by>LasBal</sys_created_by>
        <sys_created_on>2019-08-26 09:35:49</sys_created_on>
        <sys_id>031a12b0db67b700b26388805b9619a0</sys_id>
        <sys_mod_count>0</sys_mod_count>
        <sys_updated_by>LasBal</sys_updated_by>
        <sys_updated_on>2019-08-26 09:35:49</sys_updated_on>
        <value>3bf802c20a0a0b52008e2859cd8abcf2</value>
        <variable display_value="">220cd53d0a0a0b214103bdc2ec5c7ab4</variable>
    </sys_variable_value>
    <sys_variable_value action="INSERT_OR_UPDATE">
        <document>wf_activity</document>
        <document_key>4b1a12b0db67b700b26388805b96199e</document_key>
        <order>1320</order>
        <sys_class_name>sys_variable_value</sys_class_name>
        <sys_created_by>LasBal</sys_created_by>
        <sys_created_on>2019-08-26 09:35:49</sys_created_on>
        <sys_id>0f1a12b0db67b700b26388805b9619a0</sys_id>
        <sys_mod_count>0</sys_mod_count>
        <sys_updated_by>LasBal</sys_updated_by>
        <sys_updated_on>2019-08-26 09:35:49</sys_updated_on>
        <value>fef684a3dbdf1b00b26388805b9619ec</value>
        <variable display_value="">4cc4a4030a0a0b52007334f001376dc5</variable>
    </sys_variable_value>
    <sys_variable_value action="INSERT_OR_UPDATE">
        <document>wf_activity</document>
        <document_key>4b1a12b0db67b700b26388805b96199e</document_key>
        <order>1320</order>
        <sys_class_name>sys_variable_value</sys_class_name>
        <sys_created_by>LasBal</sys_created_by>
        <sys_created_on>2019-08-26 09:35:49</sys_created_on>
        <sys_id>cf1a12b0db67b700b26388805b9619a0</sys_id>
        <sys_mod_count>0</sys_mod_count>
        <sys_updated_by>LasBal</sys_updated_by>
        <sys_updated_on>2019-08-26 09:35:49</sys_updated_on>
        <value/>
        <variable display_value="">4cc6788c0a0a0b5200e6743c94001b16</variable>
    </sys_variable_value>
    <sys_variable_value action="INSERT_OR_UPDATE">
        <document>wf_activity</document>
        <document_key>4b1a12b0db67b700b26388805b96199e</document_key>
        <order>1350</order>
        <sys_class_name>sys_variable_value</sys_class_name>
        <sys_created_by>LasBal</sys_created_by>
        <sys_created_on>2019-08-26 09:35:49</sys_created_on>
        <sys_id>0b1a12b0db67b700b26388805b9619a1</sys_id>
        <sys_mod_count>0</sys_mod_count>
        <sys_updated_by>LasBal</sys_updated_by>
        <sys_updated_on>2019-08-26 09:35:49</sys_updated_on>
        <value/>
        <variable display_value="">4cc740fe0a0a0b520025dcf8e2ff78e7</variable>
    </sys_variable_value>
    <sys_variable_value action="INSERT_OR_UPDATE">
        <document>wf_activity</document>
        <document_key>4b1a12b0db67b700b26388805b96199e</document_key>
        <order>1350</order>
        <sys_class_name>sys_variable_value</sys_class_name>
        <sys_created_by>LasBal</sys_created_by>
        <sys_created_on>2019-08-26 09:35:49</sys_created_on>
        <sys_id>071a12b0db67b700b26388805b96199f</sys_id>
        <sys_mod_count>0</sys_mod_count>
        <sys_updated_by>LasBal</sys_updated_by>
        <sys_updated_on>2019-08-26 09:35:49</sys_updated_on>
        <value/>
        <variable display_value="">4cc836da0a0a0b520083ebc07da2f47c</variable>
    </sys_variable_value>
    <sys_variable_value action="INSERT_OR_UPDATE">
        <document>wf_activity</document>
        <document_key>4b1a12b0db67b700b26388805b96199e</document_key>
        <order>1360</order>
        <sys_class_name>sys_variable_value</sys_class_name>
        <sys_created_by>LasBal</sys_created_by>
        <sys_created_on>2019-08-26 09:35:49</sys_created_on>
        <sys_id>4b1a12b0db67b700b26388805b9619a0</sys_id>
        <sys_mod_count>0</sys_mod_count>
        <sys_updated_by>LasBal</sys_updated_by>
        <sys_updated_on>2019-08-26 09:35:49</sys_updated_on>
        <value/>
        <variable display_value="">292b2f0e0a0a0b215aa2dd2cbc578dc5</variable>
    </sys_variable_value>
    <sys_variable_value action="INSERT_OR_UPDATE">
        <document>wf_activity</document>
        <document_key>4b1a12b0db67b700b26388805b96199e</document_key>
        <order>1360</order>
        <sys_class_name>sys_variable_value</sys_class_name>
        <sys_created_by>LasBal</sys_created_by>
        <sys_created_on>2019-08-26 09:35:49</sys_created_on>
        <sys_id>831a12b0db67b700b26388805b9619a1</sys_id>
        <sys_mod_count>0</sys_mod_count>
        <sys_updated_by>LasBal</sys_updated_by>
        <sys_updated_on>2019-08-26 09:35:49</sys_updated_on>
        <value>1970-01-01 00:01:00</value>
        <variable display_value="">292c91070a0a0b212543d91ffde5014c</variable>
    </sys_variable_value>
    <sys_variable_value action="INSERT_OR_UPDATE">
        <document>wf_activity</document>
        <document_key>4b1a12b0db67b700b26388805b96199e</document_key>
        <order>1360</order>
        <sys_class_name>sys_variable_value</sys_class_name>
        <sys_created_by>LasBal</sys_created_by>
        <sys_created_on>2019-08-26 09:35:49</sys_created_on>
        <sys_id>871a12b0db67b700b26388805b9619a0</sys_id>
        <sys_mod_count>0</sys_mod_count>
        <sys_updated_by>LasBal</sys_updated_by>
        <sys_updated_on>2019-08-26 09:35:49</sys_updated_on>
        <value>1970-01-01 16:00:00</value>
        <variable display_value="">292bd15e0a0a0b215a040c701033e3c5</variable>
    </sys_variable_value>
    <sys_variable_value action="INSERT_OR_UPDATE">
        <document>wf_activity</document>
        <document_key>4b1a12b0db67b700b26388805b96199e</document_key>
        <order>3000</order>
        <sys_class_name>sys_variable_value</sys_class_name>
        <sys_created_by>LasBal</sys_created_by>
        <sys_created_on>2019-08-26 09:35:49</sys_created_on>
        <sys_id>8b1a12b0db67b700b26388805b96199f</sys_id>
        <sys_mod_count>0</sys_mod_count>
        <sys_updated_by>LasBal</sys_updated_by>
        <sys_updated_on>2019-08-26 09:35:49</sys_updated_on>
        <value>// Set 'answer' to the number of seconds this timer should wait&#13;
answer = 0;</value>
        <variable display_value="">293493710a0a0b2115e3e5b4fce1d12a</variable>
    </sys_variable_value>
    <wf_condition action="INSERT_OR_UPDATE">
        <activity display_value="Wait until 2 days after 'Error found at'">4b1a12b0db67b700b26388805b96199e</activity>
        <condition>activity.result != 'repair'</condition>
        <condition_default/>
        <condition_type>standard</condition_type>
        <else_flag>false</else_flag>
        <error>false</error>
        <event>false</event>
        <event_name/>
        <is_positive>false</is_positive>
        <name>Normal</name>
        <order>0</order>
        <short_description>The SLA is running normally (not being repaired)</short_description>
        <skip_during_generate>false</skip_during_generate>
        <sys_created_by>LasBal</sys_created_by>
        <sys_created_on>2019-08-26 09:35:49</sys_created_on>
        <sys_id>0f1a12b0db67b700b26388805b9619a1</sys_id>
        <sys_mod_count>0</sys_mod_count>
        <sys_updated_by>LasBal</sys_updated_by>
        <sys_updated_on>2019-08-26 09:35:49</sys_updated_on>
    </wf_condition>
    <wf_condition action="INSERT_OR_UPDATE">
        <activity display_value="Wait until 2 days after 'Error found at'">4b1a12b0db67b700b26388805b96199e</activity>
        <condition>activity.result == 'repair'</condition>
        <condition_default/>
        <condition_type>standard</condition_type>
        <else_flag>false</else_flag>
        <error>false</error>
        <event>false</event>
        <event_name/>
        <is_positive>false</is_positive>
        <name>Repair</name>
        <order>0</order>
        <short_description>The SLA is being repaired</short_description>
        <skip_during_generate>false</skip_during_generate>
        <sys_created_by>LasBal</sys_created_by>
        <sys_created_on>2019-08-26 09:35:50</sys_created_on>
        <sys_id>8f1a12b0db67b700b26388805b9619a1</sys_id>
        <sys_mod_count>0</sys_mod_count>
        <sys_updated_by>LasBal</sys_updated_by>
        <sys_updated_on>2019-08-26 09:35:50</sys_updated_on>
    </wf_condition>
    <wf_transition action="INSERT_OR_UPDATE">
        <condition display_value="Normal">0f1a12b0db67b700b26388805b9619a1</condition>
        <from display_value="Wait until 2 days after 'Error found at'">4b1a12b0db67b700b26388805b96199e</from>
        <sys_created_by>LasBal</sys_created_by>
        <sys_created_on>2019-08-26 09:35:50</sys_created_on>
        <sys_id>031a96b0db67b700b26388805b961999</sys_id>
        <sys_mod_count>0</sys_mod_count>
        <sys_updated_by>LasBal</sys_updated_by>
        <sys_updated_on>2019-08-26 09:35:50</sys_updated_on>
        <to display_value="Notify User">c71a12b0db67b700b26388805b9619a2</to>
    </wf_transition>
    <wf_transition action="INSERT_OR_UPDATE">
        <condition display_value="Incomplete">cf1a12b0db67b700b26388805b9619a4</condition>
        <from display_value="Wait for all activities to complete">0f1a12b0db67b700b26388805b9619a4</from>
        <sys_created_by>LasBal</sys_created_by>
        <sys_created_on>2019-08-26 09:35:50</sys_created_on>
        <sys_id>071a96b0db67b700b26388805b961998</sys_id>
        <sys_mod_count>0</sys_mod_count>
        <sys_updated_by>LasBal</sys_updated_by>
        <sys_updated_on>2019-08-26 09:35:50</sys_updated_on>
        <to display_value="End">cf1a96b0db67b700b26388805b961996</to>
    </wf_transition>
    <wf_transition action="INSERT_OR_UPDATE">
        <condition display_value="Always">871a12b0db67b700b26388805b9619a4</condition>
        <from display_value="Notify User, Assignee and User.Manager">8b1a12b0db67b700b26388805b9619a3</from>
        <sys_created_by>LasBal</sys_created_by>
        <sys_created_on>2019-08-26 09:35:50</sys_created_on>
        <sys_id>071a96b0db67b700b26388805b961999</sys_id>
        <sys_mod_count>0</sys_mod_count>
        <sys_updated_by>LasBal</sys_updated_by>
        <sys_updated_on>2019-08-26 09:35:50</sys_updated_on>
        <to display_value="Wait for all activities to complete">0f1a12b0db67b700b26388805b9619a4</to>
    </wf_transition>
    <wf_transition action="INSERT_OR_UPDATE">
        <condition display_value="Repair">8f1a12b0db67b700b26388805b9619a1</condition>
        <from display_value="Wait until 2 days after 'Error found at'">4b1a12b0db67b700b26388805b96199e</from>
        <sys_created_by>LasBal</sys_created_by>
        <sys_created_on>2019-08-26 09:35:50</sys_created_on>
        <sys_id>0f1a96b0db67b700b26388805b961998</sys_id>
        <sys_mod_count>0</sys_mod_count>
        <sys_updated_by>LasBal</sys_updated_by>
        <sys_updated_on>2019-08-26 09:35:50</sys_updated_on>
        <to display_value="Wait 5 working days after 'Error found at'">431a12b0db67b700b26388805b9619a6</to>
    </wf_transition>
    <wf_transition action="INSERT_OR_UPDATE">
        <condition display_value="Normal">4b1a96b0db67b700b26388805b961996</condition>
        <from display_value="Wait 5 working days after 'Error found at'">431a12b0db67b700b26388805b9619a6</from>
        <sys_created_by>LasBal</sys_created_by>
        <sys_created_on>2019-08-26 09:35:50</sys_created_on>
        <sys_id>4b1a96b0db67b700b26388805b961999</sys_id>
        <sys_mod_count>0</sys_mod_count>
        <sys_updated_by>LasBal</sys_updated_by>
        <sys_updated_on>2019-08-26 09:35:50</sys_updated_on>
        <to display_value="Notify User, Assignee and User.Manager">8b1a12b0db67b700b26388805b9619a3</to>
    </wf_transition>
    <wf_transition action="INSERT_OR_UPDATE">
        <condition display_value="Complete">431a12b0db67b700b26388805b9619a5</condition>
        <from display_value="Wait for all activities to complete">0f1a12b0db67b700b26388805b9619a4</from>
        <sys_created_by>LasBal</sys_created_by>
        <sys_created_on>2019-08-26 09:35:50</sys_created_on>
        <sys_id>831a96b0db67b700b26388805b961998</sys_id>
        <sys_mod_count>0</sys_mod_count>
        <sys_updated_by>LasBal</sys_updated_by>
        <sys_updated_on>2019-08-26 09:35:50</sys_updated_on>
        <to display_value="End">cf1a96b0db67b700b26388805b961996</to>
    </wf_transition>
    <wf_transition action="INSERT_OR_UPDATE">
        <condition display_value="Normal">0f1a12b0db67b700b26388805b9619a1</condition>
        <from display_value="Wait until 2 days after 'Error found at'">4b1a12b0db67b700b26388805b96199e</from>
        <sys_created_by>LasBal</sys_created_by>
        <sys_created_on>2019-08-26 09:35:50</sys_created_on>
        <sys_id>8b1a96b0db67b700b26388805b961998</sys_id>
        <sys_mod_count>0</sys_mod_count>
        <sys_updated_by>LasBal</sys_updated_by>
        <sys_updated_on>2019-08-26 09:35:50</sys_updated_on>
        <to display_value="Wait for all activities to complete">0f1a12b0db67b700b26388805b9619a4</to>
    </wf_transition>
    <wf_transition action="INSERT_OR_UPDATE">
        <condition display_value="Normal">0f1a12b0db67b700b26388805b9619a1</condition>
        <from display_value="Wait until 2 days after 'Error found at'">4b1a12b0db67b700b26388805b96199e</from>
        <sys_created_by>LasBal</sys_created_by>
        <sys_created_on>2019-08-26 09:35:50</sys_created_on>
        <sys_id>8f1a96b0db67b700b26388805b961998</sys_id>
        <sys_mod_count>0</sys_mod_count>
        <sys_updated_by>LasBal</sys_updated_by>
        <sys_updated_on>2019-08-26 09:35:50</sys_updated_on>
        <to display_value="Wait 5 working days after 'Error found at'">431a12b0db67b700b26388805b9619a6</to>
    </wf_transition>
    <wf_transition action="INSERT_OR_UPDATE">
        <condition display_value="Always">8b1a12b0db67b700b26388805b9619a5</condition>
        <from display_value="Begin">c71a12b0db67b700b26388805b9619a5</from>
        <sys_created_by>LasBal</sys_created_by>
        <sys_created_on>2019-08-26 09:35:50</sys_created_on>
        <sys_id>8f1a96b0db67b700b26388805b961999</sys_id>
        <sys_mod_count>0</sys_mod_count>
        <sys_updated_by>LasBal</sys_updated_by>
        <sys_updated_on>2019-08-26 09:35:50</sys_updated_on>
        <to display_value="Wait until 2 days after 'Error found at'">4b1a12b0db67b700b26388805b96199e</to>
    </wf_transition>
    <wf_transition action="INSERT_OR_UPDATE">
        <condition display_value="Always">c31a12b0db67b700b26388805b9619a3</condition>
        <from display_value="Notify User">c71a12b0db67b700b26388805b9619a2</from>
        <sys_created_by>LasBal</sys_created_by>
        <sys_created_on>2019-08-26 09:35:50</sys_created_on>
        <sys_id>c71a96b0db67b700b26388805b961998</sys_id>
        <sys_mod_count>0</sys_mod_count>
        <sys_updated_by>LasBal</sys_updated_by>
        <sys_updated_on>2019-08-26 09:35:50</sys_updated_on>
        <to display_value="Wait for all activities to complete">0f1a12b0db67b700b26388805b9619a4</to>
    </wf_transition>
    <wf_transition action="INSERT_OR_UPDATE">
        <condition display_value="Repair">c71a96b0db67b700b26388805b961996</condition>
        <from display_value="Wait 5 working days after 'Error found at'">431a12b0db67b700b26388805b9619a6</from>
        <sys_created_by>LasBal</sys_created_by>
        <sys_created_on>2019-08-26 09:35:50</sys_created_on>
        <sys_id>c71a96b0db67b700b26388805b961999</sys_id>
        <sys_mod_count>0</sys_mod_count>
        <sys_updated_by>LasBal</sys_updated_by>
        <sys_updated_on>2019-08-26 09:35:50</sys_updated_on>
        <to display_value="End">cf1a96b0db67b700b26388805b961996</to>
    </wf_transition>
    <wf_transition action="INSERT_OR_UPDATE">
        <condition display_value="Normal">4b1a96b0db67b700b26388805b961996</condition>
        <from display_value="Wait 5 working days after 'Error found at'">431a12b0db67b700b26388805b9619a6</from>
        <sys_created_by>LasBal</sys_created_by>
        <sys_created_on>2019-08-26 09:35:50</sys_created_on>
        <sys_id>cb1a96b0db67b700b26388805b961999</sys_id>
        <sys_mod_count>0</sys_mod_count>
        <sys_updated_by>LasBal</sys_updated_by>
        <sys_updated_on>2019-08-26 09:35:50</sys_updated_on>
        <to display_value="Wait for all activities to complete">0f1a12b0db67b700b26388805b9619a4</to>
    </wf_transition>
    <wf_estimated_runtime_config action="INSERT_OR_UPDATE">
        <estimated_run_time/>
        <no_of_data_points>1</no_of_data_points>
        <percentage_threshold_ert>20</percentage_threshold_ert>
        <sys_created_by>LasBal</sys_created_by>
        <sys_created_on>2019-08-26 09:35:49</sys_created_on>
        <sys_id>471a12b0db67b700b26388805b96199d</sys_id>
        <sys_mod_count>0</sys_mod_count>
        <sys_updated_by>LasBal</sys_updated_by>
        <sys_updated_on>2019-08-26 09:35:49</sys_updated_on>
        <workflow_version display_value="QC app reminder wf">c31a12b0db67b700b26388805b96199d</workflow_version>
    </wf_estimated_runtime_config>
    <wf_workflow_version action="update_multiple" query="workflow=a8daaf7adbd7f340b26388805b961974^sys_id!=c31a12b0db67b700b26388805b96199d">
        <published>false</published>
    </wf_workflow_version>
</record_update>
